LICENSE
slack_logger/__init__.py
simple_slack_logger-0.6.1.dist-info/LICENSE
simple_slack_logger-0.6.1.dist-info/WHEEL
simple_slack_logger-0.6.1.dist-info/METADATA
simple_slack_logger-0.6.1.dist-info/RECORD
