Metadata-Version: 2.1
Name: simple-slack-logger
Version: 0.6.1
Summary: Logging handler to send messages to a Slack channel.
Home-page: https://github.com/gixproject/simple-slack-logger
License: Apache
Keywords: slack,logging,notifications,webhooks
Author: giX
Author-email: viacheslavlab@gmail.com
Requires-Python: >=3.7,<4.0
Classifier: Environment :: Other Environment
Classifier: License :: OSI Approved :: Apache Software License
Classifier: License :: Other/Proprietary License
Classifier: Operating System :: OS Independent
Classifier: Programming Language :: Python :: 3
Classifier: Programming Language :: Python :: 3.7
Classifier: Programming Language :: Python :: 3.8
Classifier: Programming Language :: Python :: 3.9
Classifier: Topic :: Software Development :: Libraries :: Python Modules
Classifier: Topic :: Software Development :: Quality Assurance
Classifier: Topic :: System :: Logging
Requires-Dist: requests (>=2.23.0,<3.0.0)
